[
    {
        "name": "24/7 Cinema - Accion 8 (e)(1080)(Dual Audio)",
        "id": "247cinemaaccion8e1080dualaudio",
        "logo": "",
        "url": "http://tv.proyectox.vip:8080/PaolaPlaza/0d91a58cfda9/164783",
        "categories": [
            "24",
            "7 cinema"
        ],
        "country": ""
    },
    {
        "name": "24/7 Cinema - Amazon Prime 2 (e)(1080)(Dual Audio)",
        "id": "247cinemaamazonprime2e1080dualaudio",
        "logo": "",
        "url": "http://tv.proyectox.vip:8080/PaolaPlaza/0d91a58cfda9/164870",
        "categories": [
            "24",
            "7 cinema"
        ],
        "country": ""
    },
    {
        "name": "24/7 Cinema - Amazon Prime 4 (e)(1080)(Dual Audio)",
        "id": "247cinemaamazonprime4e1080dualaudio",
        "logo": "",
        "url": "http://tv.proyectox.vip:8080/PaolaPlaza/0d91a58cfda9/164934",
        "categories": [
            "24",
            "7 cinema"
        ],
        "country": ""
    },
    {
        "name": "24/7 Cinema - Sagas: Harry Potter (e)(4K)(Dual Audio)",
        "id": "247cinemasagasharrypottere4kdualaudio",
        "logo": "",
        "url": "http://tv.proyectox.vip:8080/PaolaPlaza/0d91a58cfda9/164971",
        "categories": [
            "24",
            "7 cinema"
        ],
        "country": ""
    },
    {
        "name": "(TR) Kurulus Orhan",
        "id": "trkurulusorhan",
        "logo": "",
        "url": "http://al01.nxtbox.de:80/arda/eqaatcM/245377",
        "categories": [
            "tr - diziler 7",
            "24"
        ],
        "country": ""
    },
    {
        "name": "(TR) Halef Koklerin Cagrisi",
        "id": "trhalefkoklerincagrisi",
        "logo": "",
        "url": "http://al01.nxtbox.de:80/arda/eqaatcM/245617",
        "categories": [
            "tr - diziler 7",
            "24"
        ],
        "country": ""
    },
    {
        "name": "(TR) Kara Sevda",
        "id": "trkarasevda",
        "logo": "",
        "url": "http://al01.nxtbox.de:80/arda/eqaatcM/207315",
        "categories": [
            "tr - diziler 7",
            "24"
        ],
        "country": ""
    },
    {
        "name": "(TR) Erkenci Kus",
        "id": "trerkencikus",
        "logo": "",
        "url": "http://al01.nxtbox.de:80/arda/eqaatcM/207321",
        "categories": [
            "tr - diziler 7",
            "24"
        ],
        "country": ""
    },
    {
        "name": "(TR) Teskilat: Sezon 4",
        "id": "trteskilatsezon4",
        "logo": "",
        "url": "http://al01.nxtbox.de:80/arda/eqaatcM/245619",
        "categories": [
            "tr - diziler 7",
            "24"
        ],
        "country": ""
    },
    {
        "name": "(TR) Kardeş Payı: Sezon 2",
        "id": "trkardepaysezon2",
        "logo": "",
        "url": "http://al01.nxtbox.de:80/arda/eqaatcM/123360",
        "categories": [
            "tr - diziler 7",
            "24"
        ],
        "country": ""
    },
    {
        "name": "(TR) Deli Yürek: Sezon 4",
        "id": "trdeliyreksezon4",
        "logo": "",
        "url": "http://al01.nxtbox.de:80/arda/eqaatcM/123404",
        "categories": [
            "tr - diziler 7",
            "24"
        ],
        "country": ""
    },
    {
        "name": "(TR) Ezel",
        "id": "trezel",
        "logo": "",
        "url": "http://al01.nxtbox.de:80/arda/eqaatcM/126604",
        "categories": [
            "tr - diziler 7",
            "24"
        ],
        "country": ""
    },
    {
        "name": "DE: SKY BOX PREMIEREN 1 HD",
        "id": "deskyboxpremieren1hd",
        "logo": "",
        "url": "http://favoritest25.shop:8080/ngn2790/ngn.504/553299",
        "categories": [
            "24",
            "7 sky box"
        ],
        "country": ""
    },
    {
        "name": "===== SHAHID LIVE =====",
        "id": "shahidlive",
        "logo": "http://shahid.mbc.net/mediaObject/shahidlogo/light/Shahid_logo_light/original/Shahid_logo_light.png",
        "url": "https://shls-live-ak.akamaized.net/out/v1/8e2419c6c7494dbba478be025af490ee/index_1.m3u8",
        "categories": [
            "24",
            "7 shahid"
        ],
        "country": ""
    },
    {
        "name": "|SHAHID| BIG TIME",
        "id": "shahidbigtime",
        "logo": "https://shahid.mbc.net/mediaObject/38f278fd-e5c1-4cd2-9d30-843550491236",
        "url": "https://shls-live-ak.akamaized.net/out/v1/07a6ab2d57b2453a91bbdd2d46b5865a/index_2.m3u8",
        "categories": [
            "24",
            "7 shahid"
        ],
        "country": ""
    },
    {
        "name": "DE : BlueTV  HARLOTS 7/24",
        "id": "debluetvharlots724",
        "logo": "http://logo.uixtreamreseller.com:8080/logo/DE/SERIES/HARTLOS.png",
        "url": "http://favoritest25.shop:8080/ngn2790/ngn.504/553366",
        "categories": [
            "24",
            "7 serien store"
        ],
        "country": ""
    },
    {
        "name": "DE: BlueTV  PRISON BREAK  24/7",
        "id": "debluetvprisonbreak247",
        "logo": "http://logo.uixtreamreseller.com:8080/logo/DE/SERIES/PRISON.BREAK.png",
        "url": "http://favoritest25.shop:8080/ngn2790/ngn.504/553369",
        "categories": [
            "24",
            "7 serien store"
        ],
        "country": ""
    },
    {
        "name": "DE: BlueTV  NEW GIRL  24/7",
        "id": "debluetvnewgirl247",
        "logo": "http://logo.uixtreamreseller.com:8080/logo/DE/SERIES/NEW.GIRL.png",
        "url": "http://favoritest25.shop:8080/ngn2790/ngn.504/553370",
        "categories": [
            "24",
            "7 serien store"
        ],
        "country": ""
    },
    {
        "name": "DE: BlueTV  COMMUNITY  24/7",
        "id": "debluetvcommunity247",
        "logo": "http://logo.uixtreamreseller.com:8080/logo/DE/SERIES/COMMUNITY.png",
        "url": "http://favoritest25.shop:8080/ngn2790/ngn.504/553374",
        "categories": [
            "24",
            "7 serien store"
        ],
        "country": ""
    },
    {
        "name": "DE: SKY SELECT 4 FHD",
        "id": "deskyselect4fhd",
        "logo": "http://logo.uixtreamreseller.com:8080/logo/DE/SELECT/04.png",
        "url": "http://favoritest25.shop:8080/ngn2790/ngn.504/553313",
        "categories": [
            "24",
            "7 sky select"
        ],
        "country": ""
    },
    {
        "name": "DE: BlueTV  AVATAR  ʜᴅ",
        "id": "debluetvavatar",
        "logo": "http://logo.uixtreamreseller.com:8080/logo/DE/KINDER.STORE/AVATAR.png",
        "url": "http://favoritest25.shop:8080/ngn2790/ngn.504/553426",
        "categories": [
            "24",
            "7 kinder store"
        ],
        "country": ""
    },
    {
        "name": "DE: BlueTV  DIE MASKE ʜᴅ",
        "id": "debluetvdiemaske",
        "logo": "http://logo.uixtreamreseller.com:8080/logo/DE/KINDER.STORE/DIE.MASKE.png",
        "url": "http://favoritest25.shop:8080/ngn2790/ngn.504/553431",
        "categories": [
            "24",
            "7 kinder store"
        ],
        "country": ""
    },
    {
        "name": "DE: MAX SELECT HD 6",
        "id": "demaxselecthd6",
        "logo": "http://logo.uixtreamreseller.com:8080/logo/DE/CINEMA.BOX/SELECT.6.png",
        "url": "http://favoritest25.shop:8080/ngn2790/ngn.504/553172",
        "categories": [
            "24",
            "7 cinema box"
        ],
        "country": ""
    },
    {
        "name": "DE: MAX SELECT  2 4K",
        "id": "demaxselect24k",
        "logo": "http://logo.uixtreamreseller.com:8080/logo/DE/CINEMA.BOX/MAX.SELECT.2.png",
        "url": "http://favoritest25.shop:8080/ngn2790/ngn.504/553182",
        "categories": [
            "24",
            "7 cinema box"
        ],
        "country": ""
    },
    {
        "name": "CINEBOX: ANIMATION",
        "id": "cineboxanimation",
        "logo": "",
        "url": "http://1tv41.icu:8080/ahx4CN/815233/119420",
        "categories": [
            "24",
            "7 channels"
        ],
        "country": ""
    },
    {
        "name": "24/7 THE FLINTSTONES",
        "id": "247theflintstones",
        "logo": "",
        "url": "http://1tv41.icu:8080/ahx4CN/815233/120949",
        "categories": [
            "24",
            "7 channels"
        ],
        "country": ""
    },
    {
        "name": "M4: Ryan Reynolds",
        "id": "m4ryanreynolds",
        "logo": "",
        "url": "http://1tv41.icu:8080/ahx4CN/815233/215368",
        "categories": [
            "24",
            "7 channels"
        ],
        "country": ""
    },
    {
        "name": "24/7 THE GOLDEN GIRLS",
        "id": "247thegoldengirls",
        "logo": "",
        "url": "http://1tv41.icu:8080/5ZCJFs/416986/120948",
        "categories": [
            "24",
            "7 channels"
        ],
        "country": ""
    },
    {
        "name": "CINEBOX: HISTORICAL",
        "id": "cineboxhistorical",
        "logo": "",
        "url": "http://1tv41.icu:8080/5ZCJFs/416986/119428",
        "categories": [
            "24",
            "7 channels"
        ],
        "country": ""
    },
    {
        "name": "CINEBOX: MYSTERY",
        "id": "cineboxmystery",
        "logo": "",
        "url": "http://1tv41.icu:8080/5ZCJFs/416986/119431",
        "categories": [
            "24",
            "7 channels"
        ],
        "country": ""
    },
    {
        "name": "CINEBOX: THRILLER",
        "id": "cineboxthriller",
        "logo": "",
        "url": "http://1tv41.icu:8080/5ZCJFs/416986/119437",
        "categories": [
            "24",
            "7 channels"
        ],
        "country": ""
    },
    {
        "name": "DOCUBOX: DISCOVERY",
        "id": "docuboxdiscovery",
        "logo": "",
        "url": "http://1tv41.icu:8080/5ZCJFs/416986/119440",
        "categories": [
            "24",
            "7 channels"
        ],
        "country": ""
    },
    {
        "name": "DOCUBOX: FRONTLINE PBS",
        "id": "docuboxfrontlinepbs",
        "logo": "",
        "url": "http://1tv41.icu:8080/5ZCJFs/416986/119444",
        "categories": [
            "24",
            "7 channels"
        ],
        "country": ""
    },
    {
        "name": "M4: Blade Runner",
        "id": "m4bladerunner",
        "logo": "",
        "url": "http://1tv41.icu:8080/5ZCJFs/416986/215277",
        "categories": [
            "24",
            "7 channels"
        ],
        "country": ""
    },
    {
        "name": "M4: Ice Age",
        "id": "m4iceage",
        "logo": "",
        "url": "http://1tv41.icu:8080/5ZCJFs/416986/215294",
        "categories": [
            "24",
            "7 channels"
        ],
        "country": ""
    },
    {
        "name": "M4: Men in Black",
        "id": "m4meninblack",
        "logo": "",
        "url": "http://1tv41.icu:8080/5ZCJFs/416986/215303",
        "categories": [
            "24",
            "7 channels"
        ],
        "country": ""
    },
    {
        "name": "M4: Oceans Eleven",
        "id": "m4oceanseleven",
        "logo": "",
        "url": "http://1tv41.icu:8080/5ZCJFs/416986/215308",
        "categories": [
            "24",
            "7 channels"
        ],
        "country": ""
    },
    {
        "name": "M4: Planet of Apes",
        "id": "m4planetofapes",
        "logo": "",
        "url": "http://1tv41.icu:8080/5ZCJFs/416986/215310",
        "categories": [
            "24",
            "7 channels"
        ],
        "country": ""
    },
    {
        "name": "M4: The Bourne",
        "id": "m4thebourne",
        "logo": "",
        "url": "http://1tv41.icu:8080/5ZCJFs/416986/215327",
        "categories": [
            "24",
            "7 channels"
        ],
        "country": ""
    },
    {
        "name": "M4: The Hunger Games",
        "id": "m4thehungergames",
        "logo": "",
        "url": "http://1tv41.icu:8080/5ZCJFs/416986/215332",
        "categories": [
            "24",
            "7 channels"
        ],
        "country": ""
    },
    {
        "name": "M4: Mark Wahlberg",
        "id": "m4markwahlberg",
        "logo": "",
        "url": "http://1tv41.icu:8080/5ZCJFs/416986/215363",
        "categories": [
            "24",
            "7 channels"
        ],
        "country": ""
    },
    {
        "name": "M4: Tom Hanks",
        "id": "m4tomhanks",
        "logo": "",
        "url": "http://1tv41.icu:8080/5ZCJFs/416986/215371",
        "categories": [
            "24",
            "7 channels"
        ],
        "country": ""
    },
    {
        "name": "M4: Denzel Washington",
        "id": "m4denzelwashington",
        "logo": "",
        "url": "http://1tv41.icu:8080/5ZCJFs/416986/215393",
        "categories": [
            "24",
            "7 channels"
        ],
        "country": ""
    },
    {
        "name": "M4: Michelle Pfeiffer",
        "id": "m4michellepfeiffer",
        "logo": "",
        "url": "http://1tv41.icu:8080/5ZCJFs/416986/215411",
        "categories": [
            "24",
            "7 channels"
        ],
        "country": ""
    },
    {
        "name": "M4: Lucy Liu",
        "id": "m4lucyliu",
        "logo": "",
        "url": "http://1tv41.icu:8080/5ZCJFs/416986/215427",
        "categories": [
            "24",
            "7 channels"
        ],
        "country": ""
    },
    {
        "name": "M4: Megan Fox",
        "id": "m4meganfox",
        "logo": "",
        "url": "http://1tv41.icu:8080/5ZCJFs/416986/215428",
        "categories": [
            "24",
            "7 channels"
        ],
        "country": ""
    },
    {
        "name": "South Park*",
        "id": "southpark",
        "logo": "",
        "url": "http://1tv41.icu:8080/ahx4CN/815233/66401",
        "categories": [
            "24",
            "7 channels"
        ],
        "country": ""
    },
    {
        "name": "CINEBOX: GREATS",
        "id": "cineboxgreats",
        "logo": "",
        "url": "http://1tv41.icu:8080/ahx4CN/815233/119426",
        "categories": [
            "24",
            "7 channels"
        ],
        "country": ""
    },
    {
        "name": "24/7 COMEDY MOVIES",
        "id": "247comedymovies",
        "logo": "",
        "url": "http://1tv41.icu:8080/ahx4CN/815233/121096",
        "categories": [
            "24",
            "7 channels"
        ],
        "country": ""
    },
    {
        "name": "24/7 DUCK TALES",
        "id": "247ducktales",
        "logo": "",
        "url": "http://1tv41.icu:8080/ahx4CN/815233/125636",
        "categories": [
            "24",
            "7 channels"
        ],
        "country": ""
    },
    {
        "name": "24/7 GUNSMOKE",
        "id": "247gunsmoke",
        "logo": "",
        "url": "http://1tv41.icu:8080/ahx4CN/815233/140069",
        "categories": [
            "24",
            "7 channels"
        ],
        "country": ""
    },
    {
        "name": "24/7 American Crime Story",
        "id": "247americancrimestory",
        "logo": "",
        "url": "http://1tv41.icu:8080/ahx4CN/815233/178876",
        "categories": [
            "24",
            "7 channels"
        ],
        "country": ""
    },
    {
        "name": "24/7 Chuck",
        "id": "247chuck",
        "logo": "",
        "url": "http://1tv41.icu:8080/ahx4CN/815233/178845",
        "categories": [
            "24",
            "7 channels"
        ],
        "country": ""
    },
    {
        "name": "M4: Action",
        "id": "m4action",
        "logo": "",
        "url": "http://1tv41.icu:8080/ahx4CN/815233/215269",
        "categories": [
            "24",
            "7 channels"
        ],
        "country": ""
    },
    {
        "name": "M4: History",
        "id": "m4history",
        "logo": "",
        "url": "http://1tv41.icu:8080/ahx4CN/815233/215292",
        "categories": [
            "24",
            "7 channels"
        ],
        "country": ""
    },
    {
        "name": "M4: The Lord of The Rings",
        "id": "m4thelordoftherings",
        "logo": "",
        "url": "http://1tv41.icu:8080/ahx4CN/815233/215334",
        "categories": [
            "24",
            "7 channels"
        ],
        "country": ""
    },
    {
        "name": "M4: The Terminator",
        "id": "m4theterminator",
        "logo": "",
        "url": "http://1tv41.icu:8080/ahx4CN/815233/215338",
        "categories": [
            "24",
            "7 channels"
        ],
        "country": ""
    },
    {
        "name": "M4: Three Flavours Cornetto",
        "id": "m4threeflavourscornetto",
        "logo": "",
        "url": "http://1tv41.icu:8080/ahx4CN/815233/215339",
        "categories": [
            "24",
            "7 channels"
        ],
        "country": ""
    },
    {
        "name": "M4: Toy Story",
        "id": "m4toystory",
        "logo": "",
        "url": "http://1tv41.icu:8080/ahx4CN/815233/215341",
        "categories": [
            "24",
            "7 channels"
        ],
        "country": ""
    },
    {
        "name": "M4: Twilight Saga",
        "id": "m4twilightsaga",
        "logo": "",
        "url": "http://1tv41.icu:8080/ahx4CN/815233/215344",
        "categories": [
            "24",
            "7 channels"
        ],
        "country": ""
    },
    {
        "name": "M4: Edward Norton",
        "id": "m4edwardnorton",
        "logo": "",
        "url": "http://1tv41.icu:8080/ahx4CN/815233/215353",
        "categories": [
            "24",
            "7 channels"
        ],
        "country": ""
    },
    {
        "name": "M4: Jim Carrey",
        "id": "m4jimcarrey",
        "logo": "",
        "url": "http://1tv41.icu:8080/ahx4CN/815233/215359",
        "categories": [
            "24",
            "7 channels"
        ],
        "country": ""
    },
    {
        "name": "M4: Tom Cruise",
        "id": "m4tomcruise",
        "logo": "",
        "url": "http://1tv41.icu:8080/ahx4CN/815233/215370",
        "categories": [
            "24",
            "7 channels"
        ],
        "country": ""
    },
    {
        "name": "M4: Anne Hathaway",
        "id": "m4annehathaway",
        "logo": "",
        "url": "http://1tv41.icu:8080/ahx4CN/815233/215385",
        "categories": [
            "24",
            "7 channels"
        ],
        "country": ""
    },
    {
        "name": "M4: Jennifer Lawrence",
        "id": "m4jenniferlawrence",
        "logo": "",
        "url": "http://1tv41.icu:8080/ahx4CN/815233/215402",
        "categories": [
            "24",
            "7 channels"
        ],
        "country": ""
    },
    {
        "name": "M4: Zoe Saldana",
        "id": "m4zoesaldana",
        "logo": "",
        "url": "http://1tv41.icu:8080/ahx4CN/815233/215433",
        "categories": [
            "24",
            "7 channels"
        ],
        "country": ""
    }
]