[
    {
        "name": "Mixed Wrestling - Covered In Your Own Jizz",
        "id": "mixedwrestlingcoveredinyourownjizz",
        "logo": "http://servicelocandine.goldsecurepro.com:80/images/b314c064af4ab1ec1e030a57cd03ba5c.png",
        "url": "http://cane.nero.ws:80/movie/cicciofro/sasy/141287.mkv",
        "categories": [
            "adulti xxx blonde"
        ],
        "country": "",
        "type": "adult"
    },
    {
        "name": "Petite School Girl Step Daughter Carolina Sweets Seduces Her Step Dad!",
        "id": "petiteschoolgirlstepdaughtercarolinasweetsseducesherstepdad",
        "logo": "http://servicelocandine.goldsecurepro.com:80/images/b314c064af4ab1ec1e030a57cd03ba5c.png",
        "url": "http://cane.nero.ws:80/movie/cicciofro/sasy/141295.mkv",
        "categories": [
            "adulti xxx blonde"
        ],
        "country": "",
        "type": "adult"
    },
    {
        "name": "Teens End Vacation With Hot Family Fuck And Facial S4:E1",
        "id": "teensendvacationwithhotfamilyfuckandfacials4e1",
        "logo": "http://servicelocandine.goldsecurepro.com:80/images/b314c064af4ab1ec1e030a57cd03ba5c.png",
        "url": "http://cane.nero.ws:80/movie/cicciofro/sasy/141312.mkv",
        "categories": [
            "adulti xxx blonde"
        ],
        "country": "",
        "type": "adult"
    },
    {
        "name": "M Mature Blonde In High Heels Takes Belly Load Of Cum From Fat Cock",
        "id": "MMatureBlondeInHighHeelsTakesBellyLoadOfCumFromFatCock.mo",
        "logo": "http://servicelocandine.goldsecurepro.com:80/images/b314c064af4ab1ec1e030a57cd03ba5c.png",
        "url": "http://cane.nero.ws:80/movie/cicciofro/sasy/141323.mkv",
        "categories": [
            "adulti xxx blonde"
        ],
        "country": "MO",
        "type": "adult"
    },
    {
        "name": "PropertySex - House Painter Smooth Talks Hot Blonde Boss Lady Into Sex",
        "id": "propertysexhousepaintersmoothtalkshotblondebossladyintosex",
        "logo": "http://servicelocandine.goldsecurepro.com:80/images/b314c064af4ab1ec1e030a57cd03ba5c.png",
        "url": "http://cane.nero.ws:80/movie/cicciofro/sasy/141328.mkv",
        "categories": [
            "adulti xxx blonde"
        ],
        "country": "",
        "type": "adult"
    },
    {
        "name": "Lesbian Squirting Nuru Massage With Bianca Stone",
        "id": "lesbiansquirtingnurumassagewithbiancastone",
        "logo": "http://servicelocandine.goldsecurepro.com:80/images/b314c064af4ab1ec1e030a57cd03ba5c.png",
        "url": "http://cane.nero.ws:80/movie/cicciofro/sasy/141305.mkv",
        "categories": [
            "adulti xxx blonde"
        ],
        "country": "",
        "type": "adult"
    },
    {
        "name": "Stepbro Fucks His Little StepSister",
        "id": "stepbrofuckshislittlestepsister",
        "logo": "http://servicelocandine.goldsecurepro.com:80/images/b314c064af4ab1ec1e030a57cd03ba5c.png",
        "url": "http://cane.nero.ws:80/movie/cicciofro/sasy/141335.mkv",
        "categories": [
            "adulti xxx blonde"
        ],
        "country": "",
        "type": "adult"
    },
    {
        "name": "Female Agent Nervous Stud Tries To Satisfy Sexy Horny Agent",
        "id": "femaleagentnervousstudtriestosatisfysexyhornyagent",
        "logo": "http://servicelocandine.goldsecurepro.com:80/images/b314c064af4ab1ec1e030a57cd03ba5c.png",
        "url": "http://cane.nero.ws:80/movie/cicciofro/sasy/141320.mkv",
        "categories": [
            "adulti xxx blonde"
        ],
        "country": "",
        "type": "adult"
    },
    {
        "name": "InnocentHigh - Blonde Teen School Girl Fucks Her Substitute Teacher",
        "id": "innocenthighblondeteenschoolgirlfuckshersubstituteteacher",
        "logo": "http://servicelocandine.goldsecurepro.com:80/images/b314c064af4ab1ec1e030a57cd03ba5c.png",
        "url": "http://cane.nero.ws:80/movie/cicciofro/sasy/141342.mkv",
        "categories": [
            "adulti xxx blonde"
        ],
        "country": "",
        "type": "adult"
    },
    {
        "name": "YFAM Step Dad Blows HUGE Load Into Soaked Pussy",
        "id": "YFAMStepDadBlowsHUGELoadIntoSoakedPussy.sp",
        "logo": "http://servicelocandine.goldsecurepro.com:80/images/b314c064af4ab1ec1e030a57cd03ba5c.png",
        "url": "http://cane.nero.ws:80/movie/cicciofro/sasy/141282.mkv",
        "categories": [
            "adulti xxx blonde"
        ],
        "country": "SP",
        "type": "adult"
    },
    {
        "name": "Alex Blake With Her StepBrother - Family Therapy",
        "id": "alexblakewithherstepbrotherfamilytherapy",
        "logo": "http://servicelocandine.goldsecurepro.com:80/images/b314c064af4ab1ec1e030a57cd03ba5c.png",
        "url": "http://cane.nero.ws:80/movie/cicciofro/sasy/141370.mkv",
        "categories": [
            "adulti xxx blonde"
        ],
        "country": "",
        "type": "adult"
    },
    {
        "name": "ExCoGi Esme Shoot 1 - Full Video - Happy Independence Day!",
        "id": "excogiesmeshoot1fullvideohappyindependenceday",
        "logo": "http://servicelocandine.goldsecurepro.com:80/images/b314c064af4ab1ec1e030a57cd03ba5c.png",
        "url": "http://cane.nero.ws:80/movie/cicciofro/sasy/141377.mkv",
        "categories": [
            "adulti xxx blonde"
        ],
        "country": "",
        "type": "adult"
    },
    {
        "name": "Goldie Rush Teasing Blowjob",
        "id": "goldierushteasingblowjob",
        "logo": "http://servicelocandine.goldsecurepro.com:80/images/b314c064af4ab1ec1e030a57cd03ba5c.png",
        "url": "http://cane.nero.ws:80/movie/cicciofro/sasy/141387.mkv",
        "categories": [
            "adulti xxx blonde"
        ],
        "country": "",
        "type": "adult"
    },
    {
        "name": "XEN Curvy Latina Is Dominated By Her Sister's Ex-Boyfriend",
        "id": "XENCurvyLatinaIsDominatedByHerSistersExBoyfriend.vi",
        "logo": "http://servicelocandine.goldsecurepro.com:80/images/b314c064af4ab1ec1e030a57cd03ba5c.png",
        "url": "http://cane.nero.ws:80/movie/cicciofro/sasy/141333.mkv",
        "categories": [
            "adulti xxx blonde"
        ],
        "country": "VI",
        "type": "adult"
    },
    {
        "name": "Euro Teen-Hot Russian Alessandra Jane Gets Her Pussy Hammered",
        "id": "euroteenhotrussianalessandrajanegetsherpussyhammered",
        "logo": "http://servicelocandine.goldsecurepro.com:80/images/b314c064af4ab1ec1e030a57cd03ba5c.png",
        "url": "http://cane.nero.ws:80/movie/cicciofro/sasy/141388.mkv",
        "categories": [
            "adulti xxx blonde"
        ],
        "country": "",
        "type": "adult"
    },
    {
        "name": "SpyFam Step Brother Catches Lesbian Step Sisters Eating Pussy",
        "id": "spyfamstepbrothercatcheslesbianstepsisterseatingpussy",
        "logo": "http://servicelocandine.goldsecurepro.com:80/images/b314c064af4ab1ec1e030a57cd03ba5c.png",
        "url": "http://cane.nero.ws:80/movie/cicciofro/sasy/141276.mkv",
        "categories": [
            "adulti xxx blonde"
        ],
        "country": "",
        "type": "adult"
    },
    {
        "name": "Tiny Teen Piper Perri Gets Destroyed On Hookup Hotshot",
        "id": "tinyteenpiperperrigetsdestroyedonhookuphotshot",
        "logo": "http://servicelocandine.goldsecurepro.com:80/images/b314c064af4ab1ec1e030a57cd03ba5c.png",
        "url": "http://cane.nero.ws:80/movie/cicciofro/sasy/141397.mkv",
        "categories": [
            "adulti xxx blonde"
        ],
        "country": "",
        "type": "adult"
    },
    {
        "name": "NNI GATA ROXXX E CANDY SMITH 2",
        "id": "NNIGATAROXXXECANDYSMITH2.di",
        "logo": "http://servicelocandine.goldsecurepro.com:80/images/b314c064af4ab1ec1e030a57cd03ba5c.png",
        "url": "http://cane.nero.ws:80/movie/cicciofro/sasy/141399.mkv",
        "categories": [
            "adulti xxx blonde"
        ],
        "country": "DI",
        "type": "adult"
    },
    {
        "name": "Nicole Aniston Bad Teacher Parody",
        "id": "nicoleanistonbadteacherparody",
        "logo": "http://servicelocandine.goldsecurepro.com:80/images/b314c064af4ab1ec1e030a57cd03ba5c.png",
        "url": "http://cane.nero.ws:80/movie/cicciofro/sasy/141409.mkv",
        "categories": [
            "adulti xxx blonde"
        ],
        "country": "",
        "type": "adult"
    },
    {
        "name": "Step Sister Sierra Nicole Gets Cream Pie On Top Of Washer By Older Brother!",
        "id": "stepsistersierranicolegetscreampieontopofwasherbyolderbrother",
        "logo": "http://servicelocandine.goldsecurepro.com:80/images/b314c064af4ab1ec1e030a57cd03ba5c.png",
        "url": "http://cane.nero.ws:80/movie/cicciofro/sasy/141391.mkv",
        "categories": [
            "adulti xxx blonde"
        ],
        "country": "",
        "type": "adult"
    },
    {
        "name": "PropertySex - Conservative Landlord Fucks Cam Girl Tenant",
        "id": "propertysexconservativelandlordfuckscamgirltenant",
        "logo": "http://servicelocandine.goldsecurepro.com:80/images/b314c064af4ab1ec1e030a57cd03ba5c.png",
        "url": "http://cane.nero.ws:80/movie/cicciofro/sasy/141410.mkv",
        "categories": [
            "adulti xxx blonde"
        ],
        "country": "",
        "type": "adult"
    },
    {
        "name": "FemaleFakeTaxi Blonde Cab Driver Loves Cock",
        "id": "femalefaketaxiblondecabdriverlovescock",
        "logo": "http://servicelocandine.goldsecurepro.com:80/images/b314c064af4ab1ec1e030a57cd03ba5c.png",
        "url": "http://cane.nero.ws:80/movie/cicciofro/sasy/141457.mkv",
        "categories": [
            "adulti xxx blonde"
        ],
        "country": "",
        "type": "adult"
    },
    {
        "name": "Dane Jones Afternoon Sex With Sweet Cute Shy Blonde Girl Next Door",
        "id": "danejonesafternoonsexwithsweetcuteshyblondegirlnextdoor",
        "logo": "http://servicelocandine.goldsecurepro.com:80/images/b314c064af4ab1ec1e030a57cd03ba5c.png",
        "url": "http://cane.nero.ws:80/movie/cicciofro/sasy/141444.mkv",
        "categories": [
            "adulti xxx blonde"
        ],
        "country": "",
        "type": "adult"
    },
    {
        "name": "Extreme Lesbian Tongue Sucking",
        "id": "ExtremeLesbianTongueSucking.hd",
        "logo": "http://servicelocandine.goldsecurepro.com:80/images/b314c064af4ab1ec1e030a57cd03ba5c.png",
        "url": "http://cane.nero.ws:80/movie/cicciofro/sasy/141402.mkv",
        "categories": [
            "adulti xxx blonde"
        ],
        "country": "HD",
        "type": "adult"
    },
    {
        "name": "FakeTaxi Hot Blonde In Tight Denim Shorts",
        "id": "faketaxihotblondeintightdenimshorts",
        "logo": "http://servicelocandine.goldsecurepro.com:80/images/b314c064af4ab1ec1e030a57cd03ba5c.png",
        "url": "http://cane.nero.ws:80/movie/cicciofro/sasy/141355.mkv",
        "categories": [
            "adulti xxx blonde"
        ],
        "country": "",
        "type": "adult"
    },
    {
        "name": "LezKiss Blondes Get Turned On Making Out In Bedroom",
        "id": "lezkissblondesgetturnedonmakingoutinbedroom",
        "logo": "http://servicelocandine.goldsecurepro.com:80/images/b314c064af4ab1ec1e030a57cd03ba5c.png",
        "url": "http://cane.nero.ws:80/movie/cicciofro/sasy/141393.mkv",
        "categories": [
            "adulti xxx blonde"
        ],
        "country": "",
        "type": "adult"
    },
    {
        "name": "Star A JCreamPie Compilation",
        "id": "starajcreampiecompilation",
        "logo": "http://servicelocandine.goldsecurepro.com:80/images/b314c064af4ab1ec1e030a57cd03ba5c.png",
        "url": "http://cane.nero.ws:80/movie/cicciofro/sasy/141359.mkv",
        "categories": [
            "adulti xxx blonde"
        ],
        "country": "",
        "type": "adult"
    },
    {
        "name": "Make Him Cuckold - His Gf Can Be Such A Whore",
        "id": "makehimcuckoldhisgfcanbesuchawhore",
        "logo": "http://servicelocandine.goldsecurepro.com:80/images/b314c064af4ab1ec1e030a57cd03ba5c.png",
        "url": "http://cane.nero.ws:80/movie/cicciofro/sasy/141447.mkv",
        "categories": [
            "adulti xxx blonde"
        ],
        "country": "",
        "type": "adult"
    },
    {
        "name": "Fake Hospital Petite Blonde Deepthroats A Thick Dick Before Rough Fuck",
        "id": "fakehospitalpetiteblondedeepthroatsathickdickbeforeroughfuck",
        "logo": "http://servicelocandine.goldsecurepro.com:80/images/b314c064af4ab1ec1e030a57cd03ba5c.png",
        "url": "http://cane.nero.ws:80/movie/cicciofro/sasy/141274.mkv",
        "categories": [
            "adulti xxx blonde"
        ],
        "country": "",
        "type": "adult"
    },
    {
        "name": "Mature Szuzanne Plays With A Young Cock",
        "id": "matureszuzanneplayswithayoungcock",
        "logo": "http://servicelocandine.goldsecurepro.com:80/images/b314c064af4ab1ec1e030a57cd03ba5c.png",
        "url": "http://cane.nero.ws:80/movie/cicciofro/sasy/141296.mkv",
        "categories": [
            "adulti xxx blonde"
        ],
        "country": "",
        "type": "adult"
    },
    {
        "name": "LLEGE RULES - Horny Teen Students Record Themselves Fucking For Money",
        "id": "LLEGERULESHornyTeenStudentsRecordThemselvesFuckingForMoney.co",
        "logo": "http://servicelocandine.goldsecurepro.com:80/images/b314c064af4ab1ec1e030a57cd03ba5c.png",
        "url": "http://cane.nero.ws:80/movie/cicciofro/sasy/141326.mkv",
        "categories": [
            "adulti xxx blonde"
        ],
        "country": "CO",
        "type": "adult"
    },
    {
        "name": "Lesbian Step Sisters Caught In The Act",
        "id": "lesbianstepsisterscaughtintheact",
        "logo": "http://servicelocandine.goldsecurepro.com:80/images/b314c064af4ab1ec1e030a57cd03ba5c.png",
        "url": "http://cane.nero.ws:80/movie/cicciofro/sasy/141327.mkv",
        "categories": [
            "adulti xxx blonde"
        ],
        "country": "",
        "type": "adult"
    },
    {
        "name": "SisLovesMe - Slutty Stepsis Offers A Helping Hand",
        "id": "sislovesmesluttystepsisoffersahelpinghand",
        "logo": "http://servicelocandine.goldsecurepro.com:80/images/b314c064af4ab1ec1e030a57cd03ba5c.png",
        "url": "http://cane.nero.ws:80/movie/cicciofro/sasy/141332.mkv",
        "categories": [
            "adulti xxx blonde"
        ],
        "country": "",
        "type": "adult"
    },
    {
        "name": "Massage Rooms Sexy MILFs Pussy Drips With Hot Come After Session With Masse",
        "id": "massageroomssexymilfspussydripswithhotcomeaftersessionwithmasse",
        "logo": "http://servicelocandine.goldsecurepro.com:80/images/b314c064af4ab1ec1e030a57cd03ba5c.png",
        "url": "http://cane.nero.ws:80/movie/cicciofro/sasy/141396.mkv",
        "categories": [
            "adulti xxx blonde"
        ],
        "country": "",
        "type": "adult"
    },
    {
        "name": "Vixen Com Sexy Blonde Fucked By Step Brother",
        "id": "vixencomsexyblondefuckedbystepbrother",
        "logo": "http://servicelocandine.goldsecurepro.com:80/images/b314c064af4ab1ec1e030a57cd03ba5c.png",
        "url": "http://cane.nero.ws:80/movie/cicciofro/sasy/141302.mkv",
        "categories": [
            "adulti xxx blonde"
        ],
        "country": "",
        "type": "adult"
    },
    {
        "name": "Tiny Teen School Girl Gets Punished By Big Cock",
        "id": "tinyteenschoolgirlgetspunishedbybigcock",
        "logo": "http://servicelocandine.goldsecurepro.com:80/images/b314c064af4ab1ec1e030a57cd03ba5c.png",
        "url": "http://cane.nero.ws:80/movie/cicciofro/sasy/141316.mkv",
        "categories": [
            "adulti xxx blonde"
        ],
        "country": "",
        "type": "adult"
    },
    {
        "name": "Mom Gives Daughter Relaxing Massage",
        "id": "momgivesdaughterrelaxingmassage",
        "logo": "http://servicelocandine.goldsecurepro.com:80/images/b314c064af4ab1ec1e030a57cd03ba5c.png",
        "url": "http://cane.nero.ws:80/movie/cicciofro/sasy/141425.mkv",
        "categories": [
            "adulti xxx blonde"
        ],
        "country": "",
        "type": "adult"
    },
    {
        "name": "Riley Reynolds (Cool Step Mom)",
        "id": "rileyreynoldscoolstepmom",
        "logo": "http://servicelocandine.goldsecurepro.com:80/images/b314c064af4ab1ec1e030a57cd03ba5c.png",
        "url": "http://cane.nero.ws:80/movie/cicciofro/sasy/141454.mkv",
        "categories": [
            "adulti xxx blonde"
        ],
        "country": "",
        "type": "adult"
    },
    {
        "name": "NM - Too Big For His Shorts",
        "id": "NMTooBigForHisShorts.cf",
        "logo": "http://servicelocandine.goldsecurepro.com:80/images/b314c064af4ab1ec1e030a57cd03ba5c.png",
        "url": "http://cane.nero.ws:80/movie/cicciofro/sasy/141461.mkv",
        "categories": [
            "adulti xxx blonde"
        ],
        "country": "CF",
        "type": "adult"
    },
    {
        "name": "Young Tiny Step Sisters Share Big Cock",
        "id": "youngtinystepsisterssharebigcock",
        "logo": "http://servicelocandine.goldsecurepro.com:80/images/b314c064af4ab1ec1e030a57cd03ba5c.png",
        "url": "http://cane.nero.ws:80/movie/cicciofro/sasy/141463.mkv",
        "categories": [
            "adulti xxx blonde"
        ],
        "country": "",
        "type": "adult"
    },
    {
        "name": "FemaleFakeTaxi Nervous Farmer Can't Satisfy Driver",
        "id": "femalefaketaxinervousfarmercantsatisfydriver",
        "logo": "http://servicelocandine.goldsecurepro.com:80/images/b314c064af4ab1ec1e030a57cd03ba5c.png",
        "url": "http://cane.nero.ws:80/movie/cicciofro/sasy/141451.mkv",
        "categories": [
            "adulti xxx blonde"
        ],
        "country": "",
        "type": "adult"
    },
    {
        "name": "Paradise Gfs - Shooting And Fucking Hot Russian Model In Paradise - Day 1",
        "id": "paradisegfsshootingandfuckinghotrussianmodelinparadiseday1",
        "logo": "http://servicelocandine.goldsecurepro.com:80/images/b314c064af4ab1ec1e030a57cd03ba5c.png",
        "url": "http://cane.nero.ws:80/movie/cicciofro/sasy/141403.mkv",
        "categories": [
            "adulti xxx blonde"
        ],
        "country": "",
        "type": "adult"
    },
    {
        "name": "Destroy My Teen Pussy Until I Cum All Over Your Thick Cock",
        "id": "destroymyteenpussyuntilicumalloveryourthickcock",
        "logo": "http://servicelocandine.goldsecurepro.com:80/images/b314c064af4ab1ec1e030a57cd03ba5c.png",
        "url": "http://cane.nero.ws:80/movie/cicciofro/sasy/141351.mkv",
        "categories": [
            "adulti xxx blonde"
        ],
        "country": "",
        "type": "adult"
    },
    {
        "name": "ACKED Cheating MILF Brandi Love’s First Big Black Cock",
        "id": "ACKEDCheatingMILFBrandiLovesFirstBigBlackCock.bl",
        "logo": "http://servicelocandine.goldsecurepro.com:80/images/b314c064af4ab1ec1e030a57cd03ba5c.png",
        "url": "http://cane.nero.ws:80/movie/cicciofro/sasy/141422.mkv",
        "categories": [
            "adulti xxx blonde"
        ],
        "country": "BL",
        "type": "adult"
    },
    {
        "name": "Cuckold Wedding Humiliation",
        "id": "cuckoldweddinghumiliation",
        "logo": "http://servicelocandine.goldsecurepro.com:80/images/b314c064af4ab1ec1e030a57cd03ba5c.png",
        "url": "http://cane.nero.ws:80/movie/cicciofro/sasy/141349.mkv",
        "categories": [
            "adulti xxx blonde"
        ],
        "country": "",
        "type": "adult"
    },
    {
        "name": "Czech Blonde Rides Taxi Driver In The Backseat",
        "id": "czechblonderidestaxidriverinthebackseat",
        "logo": "http://servicelocandine.goldsecurepro.com:80/images/b314c064af4ab1ec1e030a57cd03ba5c.png",
        "url": "http://cane.nero.ws:80/movie/cicciofro/sasy/141353.mkv",
        "categories": [
            "adulti xxx blonde"
        ],
        "country": "",
        "type": "adult"
    },
    {
        "name": "SisLovesMe - Cute Stepsis Plays For Stepbro",
        "id": "sislovesmecutestepsisplaysforstepbro",
        "logo": "http://servicelocandine.goldsecurepro.com:80/images/b314c064af4ab1ec1e030a57cd03ba5c.png",
        "url": "http://cane.nero.ws:80/movie/cicciofro/sasy/141380.mkv",
        "categories": [
            "adulti xxx blonde"
        ],
        "country": "",
        "type": "adult"
    },
    {
        "name": "YOUNG BLONDE WIFE ON BED FUCKS STRANGER HUBBY WATCHES",
        "id": "YOUNGBLONDEWIFEONBEDFUCKSSTRANGERHUBBYWATCHES.xy",
        "logo": "http://servicelocandine.goldsecurepro.com:80/images/b314c064af4ab1ec1e030a57cd03ba5c.png",
        "url": "http://cane.nero.ws:80/movie/cicciofro/sasy/141367.mkv",
        "categories": [
            "adulti xxx blonde"
        ],
        "country": "XY",
        "type": "adult"
    },
    {
        "name": "Sharing Room With Step Sister End Up Fucking Her Hard",
        "id": "sharingroomwithstepsisterendupfuckingherhard",
        "logo": "http://servicelocandine.goldsecurepro.com:80/images/b314c064af4ab1ec1e030a57cd03ba5c.png",
        "url": "http://cane.nero.ws:80/movie/cicciofro/sasy/141413.mkv",
        "categories": [
            "adulti xxx blonde"
        ],
        "country": "",
        "type": "adult"
    },
    {
        "name": "Submissive And Blindfolded Kate Truu With Endless Throat Sucks Two Cocks 1",
        "id": "submissiveandblindfoldedkatetruuwithendlessthroatsuckstwococks1",
        "logo": "http://servicelocandine.goldsecurepro.com:80/images/b314c064af4ab1ec1e030a57cd03ba5c.png",
        "url": "http://cane.nero.ws:80/movie/cicciofro/sasy/141427.mkv",
        "categories": [
            "adulti xxx blonde"
        ],
        "country": "",
        "type": "adult"
    },
    {
        "name": "Piper Perri Rides Her Babysitter And Guzzles Cum",
        "id": "piperperriridesherbabysitterandguzzlescum",
        "logo": "http://servicelocandine.goldsecurepro.com:80/images/b314c064af4ab1ec1e030a57cd03ba5c.png",
        "url": "http://cane.nero.ws:80/movie/cicciofro/sasy/141395.mkv",
        "categories": [
            "adulti xxx blonde"
        ],
        "country": "",
        "type": "adult"
    }
]