[
    {
        "name": "MKD: MRT 3",
        "id": "mkdmrt3",
        "logo": "https://docdog.top/logo/countries/MKD/MRT_3.png",
        "url": "http://vipbhbiss.top:8080/VIP015391744828611391/5a06d1aedcf0/144585",
        "categories": [
            "exyu | mkd vip"
        ],
        "country": ""
    },
    {
        "name": "MKD: M:NET KIDS",
        "id": "mkdmnetkids",
        "logo": "https://docdog.top/logo/countries/MKD/M:NET_KIDS.png",
        "url": "http://vipbhbiss.top:8080/VIP018631755037102548/1a2018c56272/144579",
        "categories": [
            "exyu | mkd vip"
        ],
        "country": ""
    },
    {
        "name": "MKD: TERA BITOLA TV",
        "id": "mkdterabitolatv",
        "logo": "https://docdog.top/logo/countries/MKD/TERA_BITOLA_TV.png",
        "url": "http://vipbhbiss.top:8080/VIP018631755037102548/1a2018c56272/144594",
        "categories": [
            "exyu | mkd vip"
        ],
        "country": ""
    },
    {
        "name": "MKD: SITEL",
        "id": "mkdsitel",
        "logo": "https://docdog.top/logo/countries/MKD/SITEL.png",
        "url": "http://vipbhbiss.top:8080/VIP011431763919048130/afa7408c7967/144588",
        "categories": [
            "exyu | mkd vip"
        ],
        "country": ""
    },
    {
        "name": "MKD: CINESTAR TV PREMIERE 1",
        "id": "mkdcinestartvpremiere1",
        "logo": "https://docdog.top/logo/countries/MKD/CINESTAR_TV_PREMIERE_1.png",
        "url": "http://vipbhbiss.top:8080/VIP01611756900902621/807c1f25a25d/144566",
        "categories": [
            "exyu | mkd vip"
        ],
        "country": ""
    },
    {
        "name": "MKD: STAR FOLK TV",
        "id": "mkdstarfolktv",
        "logo": "https://docdog.top/logo/countries/MKD/STAR_FOLK_TV.png",
        "url": "http://vipbhbiss.top:8080/VIP01661171421019072/4af4235e42b5/144591",
        "categories": [
            "exyu | mkd vip"
        ],
        "country": ""
    },
    {
        "name": "MKD: TELMA HD",
        "id": "mkdtelmahd",
        "logo": "https://docdog.top/logo/countries/MKD/TELMA_HD.png",
        "url": "http://vipbhbiss.top:8080/VIP01661171421019072/4af4235e42b5/144593",
        "categories": [
            "exyu | mkd vip"
        ],
        "country": ""
    }
]