[
    {
        "name": "(NL) RTV Drenthe",
        "id": "nlrtvdrenthe",
        "logo": "",
        "url": "http://al01.nxtbox.de:80/arda/eqaatcM/436",
        "categories": [
            "nl - regionaal"
        ],
        "country": ""
    },
    {
        "name": "(NL) Omroep Flevoland",
        "id": "nlomroepflevoland",
        "logo": "",
        "url": "http://nxtbox.uk:80/onurYagci/q2nz3S5/9788",
        "categories": [
            "nl - regionaal"
        ],
        "country": ""
    },
    {
        "name": "(NL) AT 5",
        "id": "nlat5",
        "logo": "",
        "url": "http://nxtbox.uk:80/onurYagci/q2nz3S5/1284",
        "categories": [
            "nl - regionaal"
        ],
        "country": ""
    },
    {
        "name": "(NL) Omroep Brabant",
        "id": "nlomroepbrabant",
        "logo": "",
        "url": "http://nxtbox.uk:80/onurYagci/q2nz3S5/9158",
        "categories": [
            "nl - regionaal"
        ],
        "country": ""
    },
    {
        "name": "(NL) Omrop Fryslan",
        "id": "nlomropfryslan",
        "logo": "",
        "url": "http://nxtbox.uk:80/onurYagci/q2nz3S5/9157",
        "categories": [
            "nl - regionaal"
        ],
        "country": ""
    },
    {
        "name": "(NL) RTV Oost",
        "id": "nlrtvoost",
        "logo": "",
        "url": "http://nxtbox.uk:80/onurYagci/q2nz3S5/9153",
        "categories": [
            "nl - regionaal"
        ],
        "country": ""
    },
    {
        "name": "(NL) ONS",
        "id": "nlons",
        "logo": "",
        "url": "http://nxtbox.uk:80/onurYagci/q2nz3S5/12633",
        "categories": [
            "nl - regionaal"
        ],
        "country": ""
    }
]