[
    {
        "name": "(PL) Polsat Sport 4K+",
        "id": "plpolsatsport4k",
        "logo": "",
        "url": "http://al01.nxtbox.de:80/arda/eqaatcM/22086",
        "categories": [
            "pl - sport"
        ],
        "country": ""
    },
    {
        "name": "(PL) Extreme Sports HD+",
        "id": "plextremesportshd",
        "logo": "",
        "url": "http://al01.nxtbox.de:80/arda/eqaatcM/63654",
        "categories": [
            "pl - sport"
        ],
        "country": ""
    },
    {
        "name": "(PL) Polsat Sport Fight 4K+",
        "id": "plpolsatsportfight4k",
        "logo": "",
        "url": "http://nxtbox.uk:80/onurYagci/q2nz3S5/22087",
        "categories": [
            "pl - sport"
        ],
        "country": ""
    },
    {
        "name": "(PL) Sportklub HD+",
        "id": "plsportklubhd",
        "logo": "",
        "url": "http://nxtbox.uk:80/onurYagci/q2nz3S5/63658",
        "categories": [
            "pl - sport"
        ],
        "country": ""
    },
    {
        "name": "(PL) Polsat Sport Premium 4 HD+",
        "id": "plpolsatsportpremium4hd",
        "logo": "",
        "url": "http://nxtbox.uk:80/onurYagci/q2nz3S5/202378",
        "categories": [
            "pl - sport"
        ],
        "country": ""
    },
    {
        "name": "(PL) Eleven Sports 4 4K+",
        "id": "plelevensports44k",
        "logo": "",
        "url": "http://nxtbox.uk:80/onurYagci/q2nz3S5/41767",
        "categories": [
            "pl - sport"
        ],
        "country": ""
    }
]