[
    {
        "name": "ILLING ADVENTURES OF SABRINA HD 24/7 VIP UK",
        "id": "ILLINGADVENTURESOFSABRINAHD247VIPUK.ch",
        "logo": "",
        "url": "http://porn-hub.streamtv.to:8080/Wolfgang/5he6ERunyN/118588",
        "categories": [
            "united kingdom"
        ],
        "country": "CH",
        "type": "all"
    },
    {
        "name": "PPY ENDINGS HD 24/7 VIP UK",
        "id": "PPYENDINGSHD247VIPUK.ha",
        "logo": "",
        "url": "http://porn-hub.streamtv.to:8080/Wolfgang/5he6ERunyN/118539",
        "categories": [
            "united kingdom"
        ],
        "country": "HA",
        "type": "all"
    },
    {
        "name": "IND SPOT HD 24/7 VIP UK",
        "id": "INDSPOTHD247VIPUK.bl",
        "logo": "",
        "url": "http://porn-hub.streamtv.to:8080/Wolfgang/5he6ERunyN/118602",
        "categories": [
            "united kingdom"
        ],
        "country": "BL",
        "type": "all"
    },
    {
        "name": "ILY IN PARIS HD 24/7 VIP UK",
        "id": "ILYINPARISHD247VIPUK.em",
        "logo": "",
        "url": "http://porn-hub.streamtv.to:8080/Wolfgang/5he6ERunyN/118568",
        "categories": [
            "united kingdom"
        ],
        "country": "EM",
        "type": "all"
    },
    {
        "name": "INGE HD 24/7 VIP UK",
        "id": "INGEHD247VIPUK.fr",
        "logo": "",
        "url": "http://porn-hub.streamtv.to:8080/Wolfgang/5he6ERunyN/118553",
        "categories": [
            "united kingdom"
        ],
        "country": "FR",
        "type": "all"
    },
    {
        "name": "EENLEAF HD 24/7 VIP UK",
        "id": "EENLEAFHD247VIPUK.gr",
        "logo": "",
        "url": "http://porn-hub.streamtv.to:8080/Wolfgang/5he6ERunyN/118543",
        "categories": [
            "united kingdom"
        ],
        "country": "GR",
        "type": "all"
    },
    {
        "name": "USE OF CARDS HD 24/7 VIP UK",
        "id": "USEOFCARDSHD247VIPUK.ho",
        "logo": "",
        "url": "http://porn-hub.streamtv.to:8080/Wolfgang/5he6ERunyN/118536",
        "categories": [
            "united kingdom"
        ],
        "country": "HO",
        "type": "all"
    },
    {
        "name": "RSED HD 24/7 VIP UK",
        "id": "RSEDHD247VIPUK.cu",
        "logo": "",
        "url": "http://porn-hub.streamtv.to:8080/Wolfgang/5he6ERunyN/118583",
        "categories": [
            "united kingdom"
        ],
        "country": "CU",
        "type": "all"
    },
    {
        "name": "SIGNATED SURVIVOR HD 24/7 VIP UK",
        "id": "SIGNATEDSURVIVORHD247VIPUK.de",
        "logo": "",
        "url": "http://porn-hub.streamtv.to:8080/Wolfgang/5he6ERunyN/118578",
        "categories": [
            "united kingdom"
        ],
        "country": "DE",
        "type": "all"
    },
    {
        "name": "TTLESTAR GALACTICA HD 24/7 VIP UK",
        "id": "TTLESTARGALACTICAHD247VIPUK.ba",
        "logo": "",
        "url": "http://porn-hub.streamtv.to:8080/Wolfgang/5he6ERunyN/118610",
        "categories": [
            "united kingdom"
        ],
        "country": "BA",
        "type": "all"
    },
    {
        "name": "OD GIRLS HD 24/7 VIP UK",
        "id": "ODGIRLSHD247VIPUK.go",
        "logo": "",
        "url": "http://porn-hub.streamtv.to:8080/Wolfgang/5he6ERunyN/118546",
        "categories": [
            "united kingdom"
        ],
        "country": "GO",
        "type": "all"
    },
    {
        "name": "NNIBAL HD 24/7 VIP UK",
        "id": "NNIBALHD247VIPUK.ha",
        "logo": "",
        "url": "http://porn-hub.streamtv.to:8080/Wolfgang/5he6ERunyN/118540",
        "categories": [
            "united kingdom"
        ],
        "country": "HA",
        "type": "all"
    },
    {
        "name": "ACE AND FRANKIE HD 24/7 VIP UK",
        "id": "ACEANDFRANKIEHD247VIPUK.gr",
        "logo": "",
        "url": "http://porn-hub.streamtv.to:8080/Wolfgang/5he6ERunyN/118544",
        "categories": [
            "united kingdom"
        ],
        "country": "GR",
        "type": "all"
    },
    {
        "name": "NAL SPACE HD 24/7 VIP UK",
        "id": "NALSPACEHD247VIPUK.fi",
        "logo": "",
        "url": "http://porn-hub.streamtv.to:8080/Wolfgang/5he6ERunyN/118560",
        "categories": [
            "united kingdom"
        ],
        "country": "FI",
        "type": "all"
    },
    {
        "name": "MAN EMPIRE HD 24/7 VIP UK",
        "id": "MANEMPIREHD247VIPUK.ro",
        "logo": "",
        "url": "http://porn-hub.streamtv.to:8080/Wolfgang/5he6ERunyN/118511",
        "categories": [
            "united kingdom"
        ],
        "country": "RO",
        "type": "all"
    },
    {
        "name": "EYS ANATOMY HD 24/7 VIP UK",
        "id": "EYSANATOMYHD247VIPUK.gr",
        "logo": "",
        "url": "http://porn-hub.streamtv.to:8080/Wolfgang/5he6ERunyN/118542",
        "categories": [
            "united kingdom"
        ],
        "country": "GR",
        "type": "all"
    },
    {
        "name": "N 15 HD 24/7 VIP UK",
        "id": "N15HD247VIPUK.pe",
        "logo": "",
        "url": "http://porn-hub.streamtv.to:8080/Wolfgang/5he6ERunyN/118512",
        "categories": [
            "united kingdom"
        ],
        "country": "PE",
        "type": "all"
    },
    {
        "name": "EABAG HD 24/7 VIP UK",
        "id": "EABAGHD247VIPUK.fl",
        "logo": "",
        "url": "http://porn-hub.streamtv.to:8080/Wolfgang/5he6ERunyN/118558",
        "categories": [
            "united kingdom"
        ],
        "country": "FL",
        "type": "all"
    },
    {
        "name": "RK HD 24/7 VIP UK",
        "id": "RKHD247VIPUK.da",
        "logo": "",
        "url": "http://porn-hub.streamtv.to:8080/Wolfgang/5he6ERunyN/118582",
        "categories": [
            "united kingdom"
        ],
        "country": "DA",
        "type": "all"
    },
    {
        "name": "E ORDER HD 24/7 VIP UK",
        "id": "EORDERHD247VIPUK.th",
        "logo": "",
        "url": "http://porn-hub.streamtv.to:8080/Wolfgang/5he6ERunyN/118484",
        "categories": [
            "united kingdom"
        ],
        "country": "TH",
        "type": "all"
    },
    {
        "name": "USE OF THE DRAGON HD 24/7 VIP UK",
        "id": "USEOFTHEDRAGONHD247VIPUK.ho",
        "logo": "",
        "url": "http://porn-hub.streamtv.to:8080/Wolfgang/5he6ERunyN/118535",
        "categories": [
            "united kingdom"
        ],
        "country": "HO",
        "type": "all"
    },
    {
        "name": "E MARVELOUS MRS MAISEL HD 24/7 VIP UK",
        "id": "EMARVELOUSMRSMAISELHD247VIPUK.th",
        "logo": "",
        "url": "http://porn-hub.streamtv.to:8080/Wolfgang/5he6ERunyN/118486",
        "categories": [
            "united kingdom"
        ],
        "country": "TH",
        "type": "all"
    },
    {
        "name": "RCOS MEXICO HD 24/7 VIP UK",
        "id": "RCOSMEXICOHD247VIPUK.na",
        "logo": "",
        "url": "http://porn-hub.streamtv.to:8080/Wolfgang/5he6ERunyN/118522",
        "categories": [
            "united kingdom"
        ],
        "country": "NA",
        "type": "all"
    },
    {
        "name": "E DRAGON PRINCE HD 24/7 VIP UK",
        "id": "EDRAGONPRINCEHD247VIPUK.th",
        "logo": "",
        "url": "http://porn-hub.streamtv.to:8080/Wolfgang/5he6ERunyN/118494",
        "categories": [
            "united kingdom"
        ],
        "country": "TH",
        "type": "all"
    },
    {
        "name": "EP HD 24/7 VIP UK",
        "id": "EPHD247VIPUK.ve",
        "logo": "",
        "url": "http://porn-hub.streamtv.to:8080/Wolfgang/5he6ERunyN/118469",
        "categories": [
            "united kingdom"
        ],
        "country": "VE",
        "type": "all"
    },
    {
        "name": "TREATMENT HD 24/7 VIP UK",
        "id": "TREATMENTHD247VIPUK.in",
        "logo": "",
        "url": "http://porn-hub.streamtv.to:8080/Wolfgang/5he6ERunyN/118534",
        "categories": [
            "united kingdom"
        ],
        "country": "IN",
        "type": "all"
    },
    {
        "name": "TURE MAN HD 24/7 VIP UK",
        "id": "TUREMANHD247VIPUK.fu",
        "logo": "",
        "url": "http://porn-hub.streamtv.to:8080/Wolfgang/5he6ERunyN/118551",
        "categories": [
            "united kingdom"
        ],
        "country": "FU",
        "type": "all"
    },
    {
        "name": "RVELS DAREDEVIL HD 24/7 VIP UK",
        "id": "RVELSDAREDEVILHD247VIPUK.ma",
        "logo": "",
        "url": "http://porn-hub.streamtv.to:8080/Wolfgang/5he6ERunyN/118527",
        "categories": [
            "united kingdom"
        ],
        "country": "MA",
        "type": "all"
    },
    {
        "name": "RNIVAL HD 24/7 VIP UK",
        "id": "RNIVALHD247VIPUK.ca",
        "logo": "",
        "url": "http://porn-hub.streamtv.to:8080/Wolfgang/5he6ERunyN/118594",
        "categories": [
            "united kingdom"
        ],
        "country": "CA",
        "type": "all"
    },
    {
        "name": "U HD 24/7 VIP UK",
        "id": "UHD247VIPUK.yo",
        "logo": "",
        "url": "http://porn-hub.streamtv.to:8080/Wolfgang/5he6ERunyN/118465",
        "categories": [
            "united kingdom"
        ],
        "country": "YO",
        "type": "all"
    },
    {
        "name": "BREAKABLE KIMMY SCHMIDT HD 24/7 VIP UK",
        "id": "BREAKABLEKIMMYSCHMIDTHD247VIPUK.un",
        "logo": "",
        "url": "http://porn-hub.streamtv.to:8080/Wolfgang/5he6ERunyN/118470",
        "categories": [
            "united kingdom"
        ],
        "country": "UN",
        "type": "all"
    },
    {
        "name": "ARAK HD 24/7 VIP UK",
        "id": "ARAKHD247VIPUK.oz",
        "logo": "",
        "url": "http://porn-hub.streamtv.to:8080/Wolfgang/5he6ERunyN/118514",
        "categories": [
            "united kingdom"
        ],
        "country": "OZ",
        "type": "all"
    },
    {
        "name": "E SOPRANOS HD 24/7 VIP UK",
        "id": "ESOPRANOSHD247VIPUK.th",
        "logo": "",
        "url": "http://porn-hub.streamtv.to:8080/Wolfgang/5he6ERunyN/118480",
        "categories": [
            "united kingdom"
        ],
        "country": "TH",
        "type": "all"
    },
    {
        "name": "YOND HD 24/7 VIP UK",
        "id": "YONDHD247VIPUK.be",
        "logo": "",
        "url": "http://porn-hub.streamtv.to:8080/Wolfgang/5he6ERunyN/118607",
        "categories": [
            "united kingdom"
        ],
        "country": "BE",
        "type": "all"
    },
    {
        "name": "ERLOCK HOLMES HD 24/7 VIP UK",
        "id": "ERLOCKHOLMESHD247VIPUK.sh",
        "logo": "",
        "url": "http://porn-hub.streamtv.to:8080/Wolfgang/5he6ERunyN/118505",
        "categories": [
            "united kingdom"
        ],
        "country": "SH",
        "type": "all"
    },
    {
        "name": "C One FHD UK",
        "id": "COneFHDUK.bb",
        "logo": "http://tugapt.com/picons/bbconehduk.png",
        "url": "http://porn-hub.streamtv.to:8080/Wolfgang/5he6ERunyN/1999",
        "categories": [
            "united kingdom"
        ],
        "country": "BB",
        "type": "all"
    },
    {
        "name": "LL HD 24/7 VIP UK",
        "id": "LLHD247VIPUK.bu",
        "logo": "",
        "url": "http://porn-hub.streamtv.to:8080/Wolfgang/5he6ERunyN/118596",
        "categories": [
            "united kingdom"
        ],
        "country": "BU",
        "type": "all"
    },
    {
        "name": "E BOSS BABY HD 24/7 VIP UK",
        "id": "EBOSSBABYHD247VIPUK.th",
        "logo": "",
        "url": "http://porn-hub.streamtv.to:8080/Wolfgang/5he6ERunyN/118498",
        "categories": [
            "united kingdom"
        ],
        "country": "TH",
        "type": "all"
    },
    {
        "name": "IN PEAKS HD 24/7 VIP UK",
        "id": "INPEAKSHD247VIPUK.tw",
        "logo": "",
        "url": "http://porn-hub.streamtv.to:8080/Wolfgang/5he6ERunyN/118471",
        "categories": [
            "united kingdom"
        ],
        "country": "TW",
        "type": "all"
    },
    {
        "name": "E DEUCE  HD 24/7 VIP UK",
        "id": "EDEUCEHD247VIPUK.th",
        "logo": "",
        "url": "http://porn-hub.streamtv.to:8080/Wolfgang/5he6ERunyN/118495",
        "categories": [
            "united kingdom"
        ],
        "country": "TH",
        "type": "all"
    },
    {
        "name": "OOKLYN NINE HD 24/7 VIP UK",
        "id": "OOKLYNNINEHD247VIPUK.br",
        "logo": "",
        "url": "http://porn-hub.streamtv.to:8080/Wolfgang/5he6ERunyN/118597",
        "categories": [
            "united kingdom"
        ],
        "country": "BR",
        "type": "all"
    },
    {
        "name": "X EDUCATION HD 24/7 VIP UK",
        "id": "XEDUCATIONHD247VIPUK.se",
        "logo": "",
        "url": "http://porn-hub.streamtv.to:8080/Wolfgang/5he6ERunyN/118507",
        "categories": [
            "united kingdom"
        ],
        "country": "SE",
        "type": "all"
    },
    {
        "name": "Channel 4 FHD UK",
        "id": "channel4fhduk",
        "logo": "http://tugapt.com/picons/channel4hduk.png",
        "url": "http://porn-hub.streamtv.to:8080/Wolfgang/5he6ERunyN/1971",
        "categories": [
            "united kingdom"
        ],
        "country": "",
        "type": "all"
    },
    {
        "name": "N FHD UK",
        "id": "NFHDUK.cn",
        "logo": "http://tugapt.com/picons/cnnhduk.png",
        "url": "http://porn-hub.streamtv.to:8080/Wolfgang/5he6ERunyN/1780",
        "categories": [
            "united kingdom"
        ],
        "country": "CN",
        "type": "all"
    },
    {
        "name": "R THE PEOPLE HD 24/7 VIP UK",
        "id": "RTHEPEOPLEHD247VIPUK.fo",
        "logo": "",
        "url": "http://porn-hub.streamtv.to:8080/Wolfgang/5he6ERunyN/118556",
        "categories": [
            "united kingdom"
        ],
        "country": "FO",
        "type": "all"
    },
    {
        "name": "Channel 5 FHD UK",
        "id": "channel5fhduk",
        "logo": "http://tugapt.com/picons/channel5hduk.png",
        "url": "http://porn-hub.streamtv.to:8080/Wolfgang/5he6ERunyN/1969",
        "categories": [
            "united kingdom"
        ],
        "country": "",
        "type": "all"
    },
    {
        "name": "OLLHUNTERS HD 24/7 VIP UK",
        "id": "OLLHUNTERSHD247VIPUK.tr",
        "logo": "",
        "url": "http://porn-hub.streamtv.to:8080/Wolfgang/5he6ERunyN/118473",
        "categories": [
            "united kingdom"
        ],
        "country": "TR",
        "type": "all"
    },
    {
        "name": "CTOR WHO HD 24/7 VIP UK",
        "id": "CTORWHOHD247VIPUK.do",
        "logo": "",
        "url": "http://porn-hub.streamtv.to:8080/Wolfgang/5he6ERunyN/118575",
        "categories": [
            "united kingdom"
        ],
        "country": "DO",
        "type": "all"
    },
    {
        "name": "E BABY SITTER CLUB HD 24/7 VIP UK",
        "id": "EBABYSITTERCLUBHD247VIPUK.th",
        "logo": "",
        "url": "http://porn-hub.streamtv.to:8080/Wolfgang/5he6ERunyN/118499",
        "categories": [
            "united kingdom"
        ],
        "country": "TH",
        "type": "all"
    },
    {
        "name": "OM PATROL HD 24/7 VIP UK",
        "id": "OMPATROLHD247VIPUK.do",
        "logo": "",
        "url": "http://porn-hub.streamtv.to:8080/Wolfgang/5he6ERunyN/118574",
        "categories": [
            "united kingdom"
        ],
        "country": "DO",
        "type": "all"
    },
    {
        "name": "TV FHD UK",
        "id": "TVFHDUK.mu",
        "logo": "http://tugapt.com/picons/mutvhduk.png",
        "url": "http://porn-hub.streamtv.to:8080/Wolfgang/5he6ERunyN/5736",
        "categories": [
            "united kingdom"
        ],
        "country": "MU",
        "type": "all"
    },
    {
        "name": "C Alba UK",
        "id": "CAlbaUK.bb",
        "logo": "http://tugapt.com/picons/bbcalbauk.png",
        "url": "http://porn-hub.streamtv.to:8080/Wolfgang/5he6ERunyN/5739",
        "categories": [
            "united kingdom"
        ],
        "country": "BB",
        "type": "all"
    },
    {
        "name": "AR THE WALKING DEAD HD 24/7 VIP UK",
        "id": "ARTHEWALKINGDEADHD247VIPUK.fe",
        "logo": "",
        "url": "http://porn-hub.streamtv.to:8080/Wolfgang/5he6ERunyN/118561",
        "categories": [
            "united kingdom"
        ],
        "country": "FE",
        "type": "all"
    },
    {
        "name": "IGHT OF THE CONCHORDS HD 24/7 VIP UK",
        "id": "IGHTOFTHECONCHORDSHD247VIPUK.fl",
        "logo": "",
        "url": "http://porn-hub.streamtv.to:8080/Wolfgang/5he6ERunyN/118557",
        "categories": [
            "united kingdom"
        ],
        "country": "FL",
        "type": "all"
    },
    {
        "name": "National Geographic FHD UK",
        "id": "nationalgeographicfhduk",
        "logo": "http://tugapt.com/picons/nationalgeographicuk.png",
        "url": "http://porn-hub.streamtv.to:8080/Wolfgang/5he6ERunyN/1888",
        "categories": [
            "united kingdom"
        ],
        "country": "",
        "type": "all"
    },
    {
        "name": "Premier Sports 1 FHD UK",
        "id": "premiersports1fhduk",
        "logo": "http://tugapt.com/picons/premiersportshduk.png",
        "url": "http://porn-hub.streamtv.to:8080/Wolfgang/5he6ERunyN/5737",
        "categories": [
            "united kingdom"
        ],
        "country": "",
        "type": "all"
    },
    {
        "name": "STBOUND AND DOWN HD 24/7 VIP UK",
        "id": "STBOUNDANDDOWNHD247VIPUK.ea",
        "logo": "",
        "url": "http://porn-hub.streamtv.to:8080/Wolfgang/5he6ERunyN/118571",
        "categories": [
            "united kingdom"
        ],
        "country": "EA",
        "type": "all"
    }
]