[
    {
        "name": "FC Classical Americana",
        "id": "FCClassicalAmericana.kd",
        "logo": "",
        "url": "http://cord-cutter.net:8080/KFqH4T/888412/277542",
        "categories": [
            "new radio stations"
        ],
        "country": "KD",
        "type": "all"
    },
    {
        "name": "FC Great Escape",
        "id": "FCGreatEscape.kd",
        "logo": "",
        "url": "http://cord-cutter.net:8080/KFqH4T/888412/292760",
        "categories": [
            "new radio stations"
        ],
        "country": "KD",
        "type": "all"
    },
    {
        "name": "LL 91.9 Kenai -  AK",
        "id": "LL919KenaiAK.kd",
        "logo": "",
        "url": "http://cord-cutter.net:8080/KFqH4T/888412/297591",
        "categories": [
            "new radio stations"
        ],
        "country": "KD",
        "type": "all"
    },
    {
        "name": "RP-LP \"Sun Radio\" 100.1 FM Austin -  TX",
        "id": "RPLPSunRadio1001FMAustinTX.kd",
        "logo": "",
        "url": "http://cord-cutter.net:8080/KFqH4T/888412/304610",
        "categories": [
            "new radio stations"
        ],
        "country": "KD",
        "type": "all"
    },
    {
        "name": "AL \"My 95.7\" Duluth -  MN",
        "id": "ALMy957DuluthMN.kd",
        "logo": "",
        "url": "http://cord-cutter.net:8080/KFqH4T/888412/304719",
        "categories": [
            "new radio stations"
        ],
        "country": "KD",
        "type": "all"
    },
    {
        "name": "UB 99.9FM",
        "id": "UB999FM.kd",
        "logo": "",
        "url": "http://cord-cutter.net:8080/KFqH4T/888412/308690",
        "categories": [
            "new radio stations"
        ],
        "country": "KD",
        "type": "all"
    },
    {
        "name": "JF \"CHET FM 93.5\" Ester -  AK",
        "id": "JFCHETFM935EsterAK.kd",
        "logo": "",
        "url": "http://cord-cutter.net:8080/KFqH4T/888412/309279",
        "categories": [
            "new radio stations"
        ],
        "country": "KD",
        "type": "all"
    },
    {
        "name": "KR Radio",
        "id": "KRRadio.kd",
        "logo": "",
        "url": "http://cord-cutter.net:8080/KFqH4T/888412/309821",
        "categories": [
            "new radio stations"
        ],
        "country": "KD",
        "type": "all"
    }
]