[
    {
        "name": "KITA_S7S",
        "id": "KITAS7S.ni",
        "logo": "",
        "url": "https://xc.adultiptv.net/live/XPLUS2EXTRA-uV06DVry3Z/dCE7HM6DYj/65678.m3u8",
        "categories": [
            "general"
        ],
        "country": "NI",
        "type": "all"
    },
    {
        "name": "CK",
        "id": "CK.ni",
        "logo": "https://tvassets.roarzone.net/images/55.png",
        "url": "https://edge2.roarzone.net:8447/roarzone/edge5/nickelodeon/index.m3u8?token=8f16027fc73316034ab67eadd3d995b59b359710-9e8431a5b00567de26e29adc7891d4d7-1779006398-1778995598",
        "categories": [
            "bd"
        ],
        "country": "NI",
        "type": "all"
    },
    {
        "name": "NOoHard-Engine",
        "id": "NOoHardEngine.ni",
        "logo": "",
        "url": "https://xc.adultiptv.net/live/quintino/quintinoss2650091.218.51.362086sx0e/823015.m3u8",
        "categories": [
            "general"
        ],
        "country": "NI",
        "type": "all"
    },
    {
        "name": "CK_OWEEN26",
        "id": "CKOWEEN26.ni",
        "logo": "",
        "url": "https://xc.adultiptv.net/live/07maiaramatos07/07021994ma/785341.m3u8",
        "categories": [
            "general"
        ],
        "country": "NI",
        "type": "all"
    },
    {
        "name": "COLLE__12",
        "id": "COLLE12.ni",
        "logo": "",
        "url": "https://xc.adultiptv.net/live/adultiptv/adultiptv/619377.m3u8",
        "categories": [
            "general"
        ],
        "country": "NI",
        "type": "all"
    },
    {
        "name": "NIK_STYLE",
        "id": "NIKSTYLE.ni",
        "logo": "",
        "url": "https://xc.adultiptv.net/live/rafa0102/Adtwaywdk121/805076.m3u8",
        "categories": [
            "general"
        ],
        "country": "NI",
        "type": "all"
    },
    {
        "name": "COLSKINNY1",
        "id": "COLSKINNY1.ni",
        "logo": "",
        "url": "https://xc.adultiptv.net/live/rafa0102/Adtwaywdk121/46459.m3u8",
        "categories": [
            "general"
        ],
        "country": "NI",
        "type": "all"
    },
    {
        "name": "CKJR",
        "id": "CKJR.ni",
        "logo": "https://tvassets.roarzone.net/images/nickjr.png",
        "url": "https://edge2.roarzone.net:8447/roarzone/edge5/nickjr/index.m3u8?token=3ae898be2ebb5b87a4f03e7a5a35c65ebb0a2b47-dc49f073ddd27c492d85afc479179d27-1779221737-1779210937",
        "categories": [
            "bd"
        ],
        "country": "NI",
        "type": "all"
    },
    {
        "name": "CKTOONS",
        "id": "CKTOONS.ni",
        "logo": "https://tvassets.roarzone.net/images/nicktoons.png",
        "url": "https://edge2.roarzone.net:8447/roarzone/edge5/nicktoons/index.m3u8?token=a72911b5b0f859cd15b7b6d7ed59277b73017af6-c0ca70b5e7dcaff88ac2411fe939af22-1779221737-1779210937",
        "categories": [
            "bd"
        ],
        "country": "NI",
        "type": "all"
    },
    {
        "name": "GGR_",
        "id": "GGR.ni",
        "logo": "",
        "url": "https://xc.adultiptv.net/live/sheeba/sheeba123/408830.m3u8",
        "categories": [
            "general"
        ],
        "country": "NI",
        "type": "all"
    },
    {
        "name": "GHT AT THE MUSEUM COLLECTIONS",
        "id": "GHTATTHEMUSEUMCOLLECTIONS.ni",
        "logo": "https://www.themoviedb.org/t/p/w1280/gMBMx1ig3LtlWeaD55AHEc7r5Yo.jpg",
        "url": "http://bgdc.live:25461/nmullen144/73970570/236092",
        "categories": [
            "09. 24-7 #3"
        ],
        "country": "NI",
        "type": "all"
    }
]