[
    {
        "name": "OOTF",
        "id": "OOTF.tf",
        "logo": "",
        "url": "https://xc.adultiptv.net/live/plovgisg/7illn9Z6G9/676908.m3u8",
        "categories": [
            "general"
        ],
        "country": "TF",
        "type": "all"
    },
    {
        "name": "1 Séries Films FHD FR",
        "id": "1SriesFilmsFHDFR.tf",
        "logo": "",
        "url": "http://euroserver.streamtv.to:8080/LLXnCrjcKW/wcbmH1s5qB/4113",
        "categories": [
            "general"
        ],
        "country": "TF",
        "type": "all"
    },
    {
        "name": "M RELIGION VIP AF",
        "id": "MRELIGIONVIPAF.tf",
        "logo": "",
        "url": "http://euroserver.streamtv.to:8080/LLXnCrjcKW/wcbmH1s5qB/10264",
        "categories": [
            "general"
        ],
        "country": "TF",
        "type": "all"
    }
]